randyhand
