Metadata-Version: 1.0
Name: randyhand
Version: 0.3.4
Summary: Generate random images handwritten words for OCR training
Home-page: https://github.com/a-blast/randyhand
Author: Austin Armstrong
Author-email: UNKNOWN
License: MIT
Platform: UNKNOWN
